{"id":"7667f49f-2d53-4dfd-bf4e-5fe9f8b586d5","events":[{"note":"Extraction completed: 1 field(s) suggested from PDF","type":"extraction_completed","timestamp":"2026-04-21T13:51:45.958Z"},{"note":"Tenancy inputs reviewed_overridden (rent:operator_override, months:operator_entered, date:operator_entered).","type":"tenancy_inputs_confirmed","timestamp":"2026-04-21T13:53:34.977Z"},{"note":"Preparation review complete (confirmed inputs: reviewed_overridden).","type":"tenancy_preparation_marked_ready","timestamp":"2026-04-21T13:53:41.778Z"},{"note":"Tenancy inputs reviewed_overridden (rent:operator_override, months:operator_entered, date:operator_entered).","type":"tenancy_inputs_confirmed","timestamp":"2026-04-21T13:54:29.355Z"},{"note":"Preparation review readiness invalidated because confirmed tenancy inputs changed.","type":"tenancy_preparation_readiness_invalidated","timestamp":"2026-04-21T13:54:29.355Z"},{"note":"Preparation review complete (confirmed inputs: reviewed_overridden).","type":"tenancy_preparation_marked_ready","timestamp":"2026-04-21T13:54:59.692Z"},{"note":"Tenancy inputs reviewed_overridden (rent:operator_override, months:operator_entered, date:operator_entered).","type":"tenancy_inputs_confirmed","timestamp":"2026-04-21T13:55:15.361Z"},{"note":"Preparation review readiness invalidated because confirmed tenancy inputs changed.","type":"tenancy_preparation_readiness_invalidated","timestamp":"2026-04-21T13:55:15.361Z"},{"note":"Preparation review complete (confirmed inputs: reviewed_overridden).","type":"tenancy_preparation_marked_ready","timestamp":"2026-04-21T13:55:17.547Z"},{"note":"Tenancy inputs reviewed_overridden (rent:operator_override, months:operator_entered, date:operator_entered).","type":"tenancy_inputs_confirmed","timestamp":"2026-04-21T13:55:26.191Z"},{"note":"Preparation review readiness invalidated because confirmed tenancy inputs changed.","type":"tenancy_preparation_readiness_invalidated","timestamp":"2026-04-21T13:55:26.191Z"},{"note":"Preparation review complete (confirmed inputs: reviewed_overridden).","type":"tenancy_preparation_marked_ready","timestamp":"2026-04-21T13:56:37.857Z"},{"note":"Tenancy inputs reviewed_overridden (rent:operator_override, months:operator_entered, date:operator_entered).","type":"tenancy_inputs_confirmed","timestamp":"2026-04-21T13:57:18.408Z"},{"note":"Preparation review readiness invalidated because confirmed tenancy inputs changed.","type":"tenancy_preparation_readiness_invalidated","timestamp":"2026-04-21T13:57:18.408Z"},{"note":"Preparation review complete (confirmed inputs: reviewed_overridden).","type":"tenancy_preparation_marked_ready","timestamp":"2026-04-21T13:58:30.498Z"},{"note":"Tenancy inputs reviewed_overridden (rent:operator_override, months:operator_entered, date:operator_entered).","type":"tenancy_inputs_confirmed","timestamp":"2026-04-21T13:58:33.759Z"},{"note":"Preparation review readiness invalidated because confirmed tenancy inputs changed.","type":"tenancy_preparation_readiness_invalidated","timestamp":"2026-04-21T13:58:33.759Z"},{"note":"Preparation review complete (confirmed inputs: reviewed_overridden).","type":"tenancy_preparation_marked_ready","timestamp":"2026-04-21T13:58:35.639Z"},{"note":"Portal draft created for sewa_pajakan lane","type":"portal_draft_created","timestamp":"2026-04-21T14:00:10.718Z"},{"note":"Portal draft updated for sewa_pajakan lane","type":"portal_draft_updated","timestamp":"2026-04-21T14:00:17.185Z"},{"note":"Portal draft updated for sewa_pajakan lane","type":"portal_draft_updated","timestamp":"2026-04-21T14:00:21.960Z"},{"note":"Portal draft marked ready for review (sewa_pajakan lane)","type":"portal_draft_marked_ready_for_review","timestamp":"2026-04-21T14:00:21.960Z"},{"note":"Portal draft updated for sewa_pajakan lane","type":"portal_draft_updated","timestamp":"2026-04-21T14:00:28.705Z"},{"note":"Portal draft updated for sewa_pajakan lane","type":"portal_draft_updated","timestamp":"2026-04-21T14:00:34.971Z"},{"note":"Portal draft updated for sewa_pajakan lane","type":"portal_draft_updated","timestamp":"2026-04-21T14:00:36.953Z"},{"note":"STSDS internal state refreshed. Rebuilt: portalDraft, submissionReadiness, executionPreview, automationPlan.","type":"stsds_state_refreshed","timestamp":"2026-04-21T14:00:47.371Z"},{"note":"Submission readiness: assessment_limited. Proven blockers: 0 unsatisfied. Unresolved checks: 2.","type":"submission_readiness_evaluated","timestamp":"2026-04-21T14:00:58.239Z"},{"note":"Submission readiness: assessment_limited. Proven blockers: 0 unsatisfied. Unresolved checks: 2.","type":"submission_readiness_evaluated","timestamp":"2026-04-21T14:00:59.569Z"},{"note":"Execution preview compiled: status=limited, inputs=4, targets=0, unresolved=2.","type":"execution_preview_compiled","timestamp":"2026-04-21T14:01:05.700Z"},{"note":"Portal draft updated for sewa_pajakan lane","type":"portal_draft_updated","timestamp":"2026-04-21T14:01:16.970Z"},{"note":"Execution preview compiled: status=limited, inputs=4, targets=0, unresolved=2.","type":"execution_preview_compiled","timestamp":"2026-04-21T14:01:20.346Z"},{"note":"Automation plan updated for sewa_pajakan lane (not ready)","type":"automation_plan_updated","timestamp":"2026-04-21T14:01:21.822Z"},{"note":"Automation plan updated for sewa_pajakan lane (not ready)","type":"automation_plan_updated","timestamp":"2026-04-21T14:01:22.725Z"},{"note":"Automation plan updated for sewa_pajakan lane (not ready)","type":"automation_plan_updated","timestamp":"2026-04-21T14:01:23.618Z"},{"note":"Portal draft updated for sewa_pajakan lane","type":"portal_draft_updated","timestamp":"2026-04-21T14:02:17.152Z"},{"note":"Submission readiness: assessment_limited. Proven blockers: 0 unsatisfied. Unresolved checks: 2.","type":"submission_readiness_evaluated","timestamp":"2026-04-21T14:02:24.984Z"},{"note":"Execution preview compiled: status=limited, inputs=4, targets=0, unresolved=2.","type":"execution_preview_compiled","timestamp":"2026-04-21T14:02:31.792Z"},{"note":"Portal draft updated for sewa_pajakan lane","type":"portal_draft_updated","timestamp":"2026-04-21T14:08:56.665Z"},{"note":"Portal draft updated for sewa_pajakan lane","type":"portal_draft_updated","timestamp":"2026-04-21T14:09:00.500Z"},{"note":"Portal draft updated for sewa_pajakan lane","type":"portal_draft_updated","timestamp":"2026-04-21T14:09:10.090Z"},{"note":"Browser instructions compiled for sewa_pajakan lane (not ready)","type":"browser_instructions_compiled","timestamp":"2026-04-21T14:09:16.738Z"},{"note":"Browser instructions updated for sewa_pajakan lane (not ready)","type":"browser_instructions_updated","timestamp":"2026-04-21T14:09:20.403Z"},{"note":"Automation plan updated for sewa_pajakan lane (not ready)","type":"automation_plan_updated","timestamp":"2026-04-21T14:09:23.145Z"},{"note":"Execution preview compiled: status=limited, inputs=4, targets=0, unresolved=2.","type":"execution_preview_compiled","timestamp":"2026-04-21T14:09:26.452Z"},{"note":"STSDS internal state refreshed. Rebuilt: portalDraft, submissionReadiness, executionPreview, automationPlan.","type":"stsds_state_refreshed","timestamp":"2026-04-21T14:09:29.171Z"},{"note":"Portal draft updated for sewa_pajakan lane","type":"portal_draft_updated","timestamp":"2026-04-21T14:09:30.305Z"},{"note":"Browser instructions updated for sewa_pajakan lane (not ready)","type":"browser_instructions_updated","timestamp":"2026-04-21T14:09:38.034Z"},{"note":"Submission readiness: assessment_limited. Proven blockers: 0 unsatisfied. Unresolved checks: 2.","type":"submission_readiness_evaluated","timestamp":"2026-04-21T14:10:04.946Z"},{"note":"Submission readiness: assessment_limited. Proven blockers: 0 unsatisfied. Unresolved checks: 2.","type":"submission_readiness_evaluated","timestamp":"2026-04-21T14:10:05.608Z"},{"note":"Portal draft updated for sewa_pajakan lane","type":"portal_draft_updated","timestamp":"2026-04-21T14:10:58.145Z"},{"note":"Portal draft updated for sewa_pajakan lane","type":"portal_draft_updated","timestamp":"2026-04-21T14:10:59.275Z"},{"note":"Portal draft updated for sewa_pajakan lane","type":"portal_draft_updated","timestamp":"2026-04-21T14:11:00.364Z"},{"note":"Execution preview compiled: status=limited, inputs=4, targets=0, unresolved=2.","type":"execution_preview_compiled","timestamp":"2026-04-21T14:12:35.617Z"},{"note":"Browser instructions updated for sewa_pajakan lane (not ready)","type":"browser_instructions_updated","timestamp":"2026-04-21T14:12:37.932Z"},{"note":"Submission readiness: assessment_limited. Proven blockers: 0 unsatisfied. Unresolved checks: 2.","type":"submission_readiness_evaluated","timestamp":"2026-04-21T14:13:12.949Z"},{"note":"Submission readiness: assessment_limited. Proven blockers: 0 unsatisfied. Unresolved checks: 2.","type":"submission_readiness_evaluated","timestamp":"2026-04-21T14:13:15.879Z"},{"note":"Portal draft updated for sewa_pajakan lane","type":"portal_draft_updated","timestamp":"2026-04-21T14:17:47.690Z"},{"note":"Portal draft updated for sewa_pajakan lane","type":"portal_draft_updated","timestamp":"2026-04-21T14:17:53.431Z"},{"note":"Portal draft updated for sewa_pajakan lane","type":"portal_draft_updated","timestamp":"2026-04-21T14:17:54.174Z"},{"note":"Browser instructions updated for sewa_pajakan lane (not ready)","type":"browser_instructions_updated","timestamp":"2026-04-21T14:18:18.872Z"}],"status":"uploaded","fileSize":1975664,"mimeType":"application/pdf","createdAt":"2026-04-21T13:51:11.156Z","updatedAt":"2026-04-21T14:18:18.908Z","portalDraft":{"lane":"sewa_pajakan","source":"auto_from_job","status":"ready_for_review","draftedAt":"2026-04-21T14:17:54.174Z","maklumatAmSewaPajakan":{"leaseMonths":12,"monthlyRent":4500,"stampOffice":"Kuala Lumpur","instrumentDate":"2026-01-01","receivedInMalaysiaDate":null}},"storagePath":"uploads/7667f49f-2d53-4dfd-bf4e-5fe9f8b586d5.pdf","receiptToken":"6bee4d359f5d35105bca3d081ce946b58c6366c4e2031c2d","automationPlan":{"lane":"sewa_pajakan","steps":[],"status":"not_yet_proven","createdAt":"2026-04-21T14:09:29.171Z","stepCount":0,"stopReasons":[],"intendedValues":{},"validationCheckpoints":[]},"documentCategory":"tenancy_agreement","executionPreview":{"lane":"sewa_pajakan","notes":["Limited preview — Hantar gates not yet independently proven for sewa_pajakan."],"status":"limited","generatedAt":"2026-04-21T14:12:35.617Z","intendedInputs":[{"field":"Stamp Office (Pejabat Setem Negeri)","value":"Kuala Lumpur","source":"user_entered"},{"field":"Instrument Date (Tarikh Surat Cara)","value":"2026-01-01","source":"confirmed_tenancy_input"},{"field":"Monthly Rent (RM)","value":4500,"source":"confirmed_tenancy_input"},{"field":"Lease Duration (months)","value":12,"source":"confirmed_tenancy_input"}],"unresolvedSteps":["Hantar gates not yet proven for this lane","Additional portal checks may still apply"],"validationTargets":[],"preparationSummary":{"declarationPrepared":false,"bahagianAFirstPartyPrepared":false,"bahagianASecondPartyPrepared":false}},"extractionResult":{"dataSource":"pdf_parsed_unverified","extractedAt":"2026-04-21T13:51:45.958Z","ocrAttempted":false,"fieldsExtracted":1,"textLengthChars":26616,"suggestedLeaseMonths":{"value":null,"source":null,"confidence":null},"suggestedMonthlyRent":{"value":12,"source":"pdf_text_pattern","matchNote":"RM X per month","confidence":"medium"},"suggestedAgreementDate":{"value":null,"source":null,"confidence":null}},"originalFileName":"Tenancy Agreement- Testing for stamping.pdf","routingSuggestion":{"source":"category_match","confidence":"high","suggestedAt":"2026-04-21T13:51:44.287Z","suggestedLane":"sewa_pajakan","suggestedPortalDocumentName":null,"expectedDerivedDocumentGroup":null,"observedEditableInstrumentCategory":null},"browserInstructions":{"lane":"sewa_pajakan","status":"not_yet_proven","compiledAt":"2026-04-21T14:18:18.872Z","instructions":[],"advisoryNotes":["Browser instruction set not yet independently proven for this lane."],"blockedReasons":[],"instructionCount":0},"submissionReadiness":{"lane":"sewa_pajakan","notes":["Hantar gates not yet independently proven for sewa_pajakan.","No real readiness judgment is possible until live exploration confirms the gates for this lane."],"status":"assessment_limited","evaluatedAt":"2026-04-21T14:13:15.878Z","provenBlockers":[],"unresolvedChecks":["Lampiran (document uploads) may be required — not yet confirmed as a Hantar gate","Additional server-side validation may exist beyond the proven gates"],"gatesProvenForLane":false},"confirmedTenancyInputs":{"confirmedAt":"2026-04-21T13:58:33.759Z","reviewStatus":"reviewed_overridden","confirmedBySource":{"leaseMonths":"operator_entered","monthlyRent":"operator_override","agreementDate":"operator_entered"},"confirmedLeaseMonths":12,"confirmedMonthlyRent":4500,"confirmedAgreementDate":"2026-01-01"},"supportedForAutomation":true,"tenancyPreparationReadiness":{"basis":{"reviewStatus":"reviewed_overridden","hasExtraction":true,"hasConfirmedInputs":true},"source":"operator_marked","markedReadyAt":"2026-04-21T13:58:35.639Z"}}